{
  "token": "8898d9adb0a2dbd2",
  "name": "资料管理员入门简历模板",
  "desc": "资料管理员入门简历模板，适合应届生招聘投递，也适合其他相关岗位简历参考",
  "long_desc": "这款“资料管理员入门简历模板”是专为应届毕业生量身打造的求职利器，同时也非常适合其他相关岗位求职者参考。它简洁明了的设计风格，能够帮助你清晰地展示个人信息、教育背景、技能特长以及实习/项目经历。模板结构清晰，重点突出，方便HR快速捕捉关键信息。特别针对资料管理员岗位，我们优化了技能展示部分，强调了信息管理、文档处理等相关能力。即使你没有丰富的工作经验，也能通过该模板突出你的学习能力和潜力。此外，模板的可编辑性强，方便你根据自身情况进行个性化调整，打造一份专属的求职简历。特别是在校招季，一份精心准备的简历能让你在众多应聘者中脱颖而出。您可通过下方的模板摘取您需要的内容，然后使用我们AI驱动的简历",
  "seo_title": "资料管理员入门简历模板 | 免费行政简历制作下载_超级简历WonderCV",
  "seo_description": "精选资料管理员入门简历模板免费下载，提供0年行政经验简历模版范文，专为Office、档案管理系统、公文写作等技能优化方便简历制作， 适配资料管理员岗位要求，帮您高效制作简历",
  "seo_keywords": "免费下载资料管理员入门简历模板，行政助理简历模板,文档管理员简历模板,行政简历制作,Office技能简历,档案管理系统技能简历,CET-4简历",
  "lang": "cn",
  "roles": [
    "应届生简历模板",
    "求职简历模板",
    "实习生简历模板",
    "校招简历"
  ],
  "tags_cn": [
    "应届生简历模板",
    "求职简历模板",
    "实习生简历模板",
    "校招简历"
  ],
  "tags_en": [
    "yingjiesheng",
    "qiuzhi",
    "shixisheng",
    "xiaozhao"
  ],
  "ats_friendly": true,
  "unlock": null,
  "price": 0.0,
  "people_count": 789562,
  "img": "https://logo.wondercv.com/resumes-img/xOAG-LN5_259abd.png",
  "profession_name": null,
  "highlights": [
    "专为资料管理员岗位设计",
    "适合应届生和入门级求职者",
    "简洁清晰，重点突出",
    "强调信息管理相关技能",
    "易于编辑，方便个性化定制"
  ],
  "wondercv_url": "https://www.wondercv.com/jianlimoban/8898d9adb0a2dbd2.html",
  "cv_token": "xOAG-LN5"
}